{
  "name": "text-fill-animation",
  "type": "registry:component",
  "title": "Text Fill Animation",
  "description": "Scroll-synced text color fill animation with customizable color sweep effect",
  "category": "text",
  "categories": [
    "text"
  ],
  "tier": "pro",
  "dependencies": [
    "gsap"
  ],
  "registryDependencies": [],
  "previewUrl": "/text-fill-animation",
  "coverImage": "/assets/list/text-fill-animation.png",
  "videoUrl": "text-fill-animation.mp4",
  "files": [
    {
      "path": "text-fill-animation.jsx",
      "type": "registry:component",
      "target": "components/hyperiux/text-fill-animation.jsx"
    }
  ]
}